jinns/__init__.py
jinns/data/_AbstractDataGenerator.py
jinns/data/_Batchs.py
jinns/data/_CubicMeshPDENonStatio.py
jinns/data/_CubicMeshPDEStatio.py
jinns/data/_DataGeneratorODE.py
jinns/data/_DataGeneratorObservations.py
jinns/data/_DataGeneratorParameter.py
jinns/data/__init__.py
jinns/data/_utils.py
jinns/experimental/__init__.py
jinns/experimental/_diffrax_solver.py
jinns/loss/_DynamicLoss.py
jinns/loss/_DynamicLossAbstract.py
jinns/loss/_LossODE.py
jinns/loss/_LossPDE.py
jinns/loss/__init__.py
jinns/loss/_abstract_loss.py
jinns/loss/_boundary_conditions.py
jinns/loss/_loss_components.py
jinns/loss/_loss_utils.py
jinns/loss/_loss_weight_updates.py
jinns/loss/_loss_weights.py
jinns/loss/_operators.py
jinns/nn/__init__.py
jinns/nn/_abstract_pinn.py
jinns/nn/_hyperpinn.py
jinns/nn/_mlp.py
jinns/nn/_pinn.py
jinns/nn/_ppinn.py
jinns/nn/_save_load.py
jinns/nn/_spinn.py
jinns/nn/_spinn_mlp.py
jinns/nn/_utils.py
jinns/parameters/__init__.py
jinns/parameters/_derivative_keys.py
jinns/parameters/_params.py
jinns/plot/__init__.py
jinns/plot/_plot.py
jinns/solver/__init__.py
jinns/solver/_rar.py
jinns/solver/_solve.py
jinns/solver/_solve_alternate.py
jinns/solver/_utils.py
jinns/utils/_DictToModuleMeta.py
jinns/utils/_ItemizableModule.py
jinns/utils/__init__.py
jinns/utils/_containers.py
jinns/utils/_types.py
jinns/utils/_utils.py
jinns/validation/__init__.py
jinns/validation/_validation.py
jinns-1.7.0.dist-info/licenses/AUTHORS
jinns-1.7.0.dist-info/licenses/LICENSE
jinns-1.7.0.dist-info/METADATA
jinns-1.7.0.dist-info/WHEEL
jinns-1.7.0.dist-info/top_level.txt
jinns-1.7.0.dist-info/RECORD
