Metadata-Version: 2.4
Name: jinns
Version: 1.7.0
Summary: Physics Informed Neural Network with JAX
Author-email: Hugo Gangloff <hugo.gangloff@inrae.fr>, Nicolas Jouvin <nicolas.jouvin@inrae.fr>
Maintainer-email: Hugo Gangloff <hugo.gangloff@inrae.fr>, Nicolas Jouvin <nicolas.jouvin@inrae.fr>
License: Apache License 2.0
Project-URL: Repository, https://gitlab.com/mia_jinns/jinns
Project-URL: Documentation, https://mia_jinns.gitlab.io/jinns/index.html
Classifier: License :: OSI Approved :: Apache Software License
Classifier: Development Status :: 5 - Production/Stable
Classifier: Programming Language :: Python
Requires-Python: >=3.11
License-File: LICENSE
License-File: AUTHORS
Requires-Dist: numpy>=2.0.0
Requires-Dist: jax>=0.8.1
Requires-Dist: optax>=0.2.6
Requires-Dist: equinox>=0.13.2
Requires-Dist: matplotlib
Requires-Dist: jaxtyping
Provides-Extra: notebook
Requires-Dist: jupyter; extra == "notebook"
Requires-Dist: seaborn; extra == "notebook"
Requires-Dist: pandas; extra == "notebook"
Requires-Dist: pytest; extra == "notebook"
Requires-Dist: pre-commit; extra == "notebook"
Requires-Dist: pyright; extra == "notebook"
Requires-Dist: diffrax; extra == "notebook"
Dynamic: license-file
